{
  "version": 1,
  "book": {
    "id": "sharah-kitab-al-tawheed",
    "title": "Sharah Kitab al-Tawheed",
    "titleArabic": "شرح كتاب التوحيد",
    "author": "Muhammad ibn Abd al-Wahhab",
    "speaker": "Fazilat Shaikh Abdullah Nasir Rahmani Hafizahullah",
    "speakerShortName": "Shaikh Abdullah Nasir Rahmani",
    "totalDurationSeconds": 97617,
    "lectureCount": 50,
    "coverImageUrl": "https://al-tawheed-content.pages.dev/tawheed/cover.jpg",
    "language": "Urdu",
    "catalogUpdatedAt": "2026-05-30T00:00:00Z"
  },
  "chapters": [
    {
      "id": "class-01",
      "number": 1,
      "title": "Class 01",
      "lectureCount": 2
    },
    {
      "id": "class-02",
      "number": 2,
      "title": "Class 02",
      "lectureCount": 3
    },
    {
      "id": "class-03",
      "number": 3,
      "title": "Class 03",
      "lectureCount": 3
    },
    {
      "id": "class-04",
      "number": 4,
      "title": "Class 04",
      "lectureCount": 3
    },
    {
      "id": "class-05",
      "number": 5,
      "title": "Class 05",
      "lectureCount": 4
    },
    {
      "id": "class-06",
      "number": 6,
      "title": "Class 06",
      "lectureCount": 4
    },
    {
      "id": "class-07",
      "number": 7,
      "title": "Class 07",
      "lectureCount": 2
    },
    {
      "id": "class-08",
      "number": 8,
      "title": "Class 08",
      "lectureCount": 4
    },
    {
      "id": "class-09",
      "number": 9,
      "title": "Class 09",
      "lectureCount": 2
    },
    {
      "id": "class-10",
      "number": 10,
      "title": "Class 10",
      "lectureCount": 4
    },
    {
      "id": "class-11",
      "number": 11,
      "title": "Class 11",
      "lectureCount": 4
    },
    {
      "id": "class-12",
      "number": 12,
      "title": "Class 12",
      "lectureCount": 5
    },
    {
      "id": "class-13",
      "number": 13,
      "title": "Class 13",
      "lectureCount": 3
    },
    {
      "id": "class-14",
      "number": 14,
      "title": "Class 14",
      "lectureCount": 5
    },
    {
      "id": "class-15",
      "number": 15,
      "title": "Class 15",
      "lectureCount": 2
    }
  ],
  "lectures": [
    {
      "id": "lec-001",
      "number": 1,
      "chapterId": "class-01",
      "title": "Class 01 — Part 01",
      "audioUrl": "https://pub-8a0d3971e9fd4d7c991d2300ca9bdca5.r2.dev/lec-001.mp3",
      "durationSeconds": 2157,
      "fileSizeBytes": 8628602,
      "description": null
    },
    {
      "id": "lec-002",
      "number": 2,
      "chapterId": "class-01",
      "title": "Class 01 — Part 02",
      "audioUrl": "https://pub-8a0d3971e9fd4d7c991d2300ca9bdca5.r2.dev/lec-002.mp3",
      "durationSeconds": 2056,
      "fileSizeBytes": 8226630,
      "description": null
    },
    {
      "id": "lec-003",
      "number": 3,
      "chapterId": "class-02",
      "title": "Class 02 — Part 01",
      "audioUrl": "https://pub-8a0d3971e9fd4d7c991d2300ca9bdca5.r2.dev/lec-003.mp3",
      "durationSeconds": 2494,
      "fileSizeBytes": 9978611,
      "description": null
    },
    {
      "id": "lec-004",
      "number": 4,
      "chapterId": "class-02",
      "title": "Class 02 — Part 02",
      "audioUrl": "https://pub-8a0d3971e9fd4d7c991d2300ca9bdca5.r2.dev/lec-004.mp3",
      "durationSeconds": 2230,
      "fileSizeBytes": 8922741,
      "description": null
    },
    {
      "id": "lec-005",
      "number": 5,
      "chapterId": "class-02",
      "title": "Class 02 — Part 03",
      "audioUrl": "https://pub-8a0d3971e9fd4d7c991d2300ca9bdca5.r2.dev/lec-005.mp3",
      "durationSeconds": 1635,
      "fileSizeBytes": 6540583,
      "description": null
    },
    {
      "id": "lec-006",
      "number": 6,
      "chapterId": "class-03",
      "title": "Class 03 — Part 01",
      "audioUrl": "https://pub-8a0d3971e9fd4d7c991d2300ca9bdca5.r2.dev/lec-006.mp3",
      "durationSeconds": 1984,
      "fileSizeBytes": 7938552,
      "description": null
    },
    {
      "id": "lec-007",
      "number": 7,
      "chapterId": "class-03",
      "title": "Class 03 — Part 02",
      "audioUrl": "https://pub-8a0d3971e9fd4d7c991d2300ca9bdca5.r2.dev/lec-007.mp3",
      "durationSeconds": 2254,
      "fileSizeBytes": 9018663,
      "description": null
    },
    {
      "id": "lec-008",
      "number": 8,
      "chapterId": "class-03",
      "title": "Class 03 — Part 03",
      "audioUrl": "https://pub-8a0d3971e9fd4d7c991d2300ca9bdca5.r2.dev/lec-008.mp3",
      "durationSeconds": 2311,
      "fileSizeBytes": 9246660,
      "description": null
    },
    {
      "id": "lec-009",
      "number": 9,
      "chapterId": "class-04",
      "title": "Class 04 — Part 01",
      "audioUrl": "https://pub-8a0d3971e9fd4d7c991d2300ca9bdca5.r2.dev/lec-009.mp3",
      "durationSeconds": 2613,
      "fileSizeBytes": 10452576,
      "description": null
    },
    {
      "id": "lec-010",
      "number": 10,
      "chapterId": "class-04",
      "title": "Class 04 — Part 02",
      "audioUrl": "https://pub-8a0d3971e9fd4d7c991d2300ca9bdca5.r2.dev/lec-010.mp3",
      "durationSeconds": 2377,
      "fileSizeBytes": 9510601,
      "description": null
    },
    {
      "id": "lec-011",
      "number": 11,
      "chapterId": "class-04",
      "title": "Class 04 — Part 03",
      "audioUrl": "https://pub-8a0d3971e9fd4d7c991d2300ca9bdca5.r2.dev/lec-011.mp3",
      "durationSeconds": 2835,
      "fileSizeBytes": 11340531,
      "description": null
    },
    {
      "id": "lec-012",
      "number": 12,
      "chapterId": "class-05",
      "title": "Class 05 — Part 01",
      "audioUrl": "https://pub-8a0d3971e9fd4d7c991d2300ca9bdca5.r2.dev/lec-012.mp3",
      "durationSeconds": 1981,
      "fileSizeBytes": 7926535,
      "description": null
    },
    {
      "id": "lec-013",
      "number": 13,
      "chapterId": "class-05",
      "title": "Class 05 — Part 02",
      "audioUrl": "https://pub-8a0d3971e9fd4d7c991d2300ca9bdca5.r2.dev/lec-013.mp3",
      "durationSeconds": 1915,
      "fileSizeBytes": 7662594,
      "description": null
    },
    {
      "id": "lec-014",
      "number": 14,
      "chapterId": "class-05",
      "title": "Class 05 — Part 03",
      "audioUrl": "https://pub-8a0d3971e9fd4d7c991d2300ca9bdca5.r2.dev/lec-014.mp3",
      "durationSeconds": 1659,
      "fileSizeBytes": 6636609,
      "description": null
    },
    {
      "id": "lec-015",
      "number": 15,
      "chapterId": "class-05",
      "title": "Class 05 — Part 04",
      "audioUrl": "https://pub-8a0d3971e9fd4d7c991d2300ca9bdca5.r2.dev/lec-015.mp3",
      "durationSeconds": 1696,
      "fileSizeBytes": 6786552,
      "description": null
    },
    {
      "id": "lec-016",
      "number": 16,
      "chapterId": "class-06",
      "title": "Class 06 — Part 01",
      "audioUrl": "https://pub-8a0d3971e9fd4d7c991d2300ca9bdca5.r2.dev/lec-016.mp3",
      "durationSeconds": 2299,
      "fileSizeBytes": 9198699,
      "description": null
    },
    {
      "id": "lec-017",
      "number": 17,
      "chapterId": "class-06",
      "title": "Class 06 — Part 02",
      "audioUrl": "https://pub-8a0d3971e9fd4d7c991d2300ca9bdca5.r2.dev/lec-017.mp3",
      "durationSeconds": 1554,
      "fileSizeBytes": 6216664,
      "description": null
    },
    {
      "id": "lec-018",
      "number": 18,
      "chapterId": "class-06",
      "title": "Class 06 — Part 03",
      "audioUrl": "https://pub-8a0d3971e9fd4d7c991d2300ca9bdca5.r2.dev/lec-018.mp3",
      "durationSeconds": 1867,
      "fileSizeBytes": 7470542,
      "description": null
    },
    {
      "id": "lec-019",
      "number": 19,
      "chapterId": "class-06",
      "title": "Class 06 — Part 04",
      "audioUrl": "https://pub-8a0d3971e9fd4d7c991d2300ca9bdca5.r2.dev/lec-019.mp3",
      "durationSeconds": 2131,
      "fileSizeBytes": 8526620,
      "description": null
    },
    {
      "id": "lec-020",
      "number": 20,
      "chapterId": "class-07",
      "title": "Class 07 — Part 01",
      "audioUrl": "https://pub-8a0d3971e9fd4d7c991d2300ca9bdca5.r2.dev/lec-020.mp3",
      "durationSeconds": 1915,
      "fileSizeBytes": 7662594,
      "description": null
    },
    {
      "id": "lec-021",
      "number": 21,
      "chapterId": "class-07",
      "title": "Class 07 — Part 02",
      "audioUrl": "https://pub-8a0d3971e9fd4d7c991d2300ca9bdca5.r2.dev/lec-021.mp3",
      "durationSeconds": 1852,
      "fileSizeBytes": 7410774,
      "description": null
    },
    {
      "id": "lec-022",
      "number": 22,
      "chapterId": "class-08",
      "title": "Class 08 — Part 01",
      "audioUrl": "https://pub-8a0d3971e9fd4d7c991d2300ca9bdca5.r2.dev/lec-022.mp3",
      "durationSeconds": 1678,
      "fileSizeBytes": 6714663,
      "description": null
    },
    {
      "id": "lec-023",
      "number": 23,
      "chapterId": "class-08",
      "title": "Class 08 — Part 02",
      "audioUrl": "https://pub-8a0d3971e9fd4d7c991d2300ca9bdca5.r2.dev/lec-023.mp3",
      "durationSeconds": 1968,
      "fileSizeBytes": 7872619,
      "description": null
    },
    {
      "id": "lec-024",
      "number": 24,
      "chapterId": "class-08",
      "title": "Class 08 — Part 03",
      "audioUrl": "https://pub-8a0d3971e9fd4d7c991d2300ca9bdca5.r2.dev/lec-024.mp3",
      "durationSeconds": 1711,
      "fileSizeBytes": 6846529,
      "description": null
    },
    {
      "id": "lec-025",
      "number": 25,
      "chapterId": "class-08",
      "title": "Class 08 — Part 04",
      "audioUrl": "https://pub-8a0d3971e9fd4d7c991d2300ca9bdca5.r2.dev/lec-025.mp3",
      "durationSeconds": 1953,
      "fileSizeBytes": 7812642,
      "description": null
    },
    {
      "id": "lec-026",
      "number": 26,
      "chapterId": "class-09",
      "title": "Class 09 — Part 01",
      "audioUrl": "https://pub-8a0d3971e9fd4d7c991d2300ca9bdca5.r2.dev/lec-026.mp3",
      "durationSeconds": 1884,
      "fileSizeBytes": 7536684,
      "description": null
    },
    {
      "id": "lec-027",
      "number": 27,
      "chapterId": "class-09",
      "title": "Class 09 — Part 02",
      "audioUrl": "https://pub-8a0d3971e9fd4d7c991d2300ca9bdca5.r2.dev/lec-027.mp3",
      "durationSeconds": 2611,
      "fileSizeBytes": 10446516,
      "description": null
    },
    {
      "id": "lec-028",
      "number": 28,
      "chapterId": "class-10",
      "title": "Class 10 — Part 01",
      "audioUrl": "https://pub-8a0d3971e9fd4d7c991d2300ca9bdca5.r2.dev/lec-028.mp3",
      "durationSeconds": 1612,
      "fileSizeBytes": 6450513,
      "description": null
    },
    {
      "id": "lec-029",
      "number": 29,
      "chapterId": "class-10",
      "title": "Class 10 — Part 02",
      "audioUrl": "https://pub-8a0d3971e9fd4d7c991d2300ca9bdca5.r2.dev/lec-029.mp3",
      "durationSeconds": 1822,
      "fileSizeBytes": 7290506,
      "description": null
    },
    {
      "id": "lec-030",
      "number": 30,
      "chapterId": "class-10",
      "title": "Class 10 — Part 03",
      "audioUrl": "https://pub-8a0d3971e9fd4d7c991d2300ca9bdca5.r2.dev/lec-030.mp3",
      "durationSeconds": 1915,
      "fileSizeBytes": 7662594,
      "description": null
    },
    {
      "id": "lec-031",
      "number": 31,
      "chapterId": "class-10",
      "title": "Class 10 — Part 04",
      "audioUrl": "https://pub-8a0d3971e9fd4d7c991d2300ca9bdca5.r2.dev/lec-031.mp3",
      "durationSeconds": 2230,
      "fileSizeBytes": 8922741,
      "description": null
    },
    {
      "id": "lec-032",
      "number": 32,
      "chapterId": "class-11",
      "title": "Class 11 — Part 01",
      "audioUrl": "https://pub-8a0d3971e9fd4d7c991d2300ca9bdca5.r2.dev/lec-032.mp3",
      "durationSeconds": 1837,
      "fileSizeBytes": 7350588,
      "description": null
    },
    {
      "id": "lec-033",
      "number": 33,
      "chapterId": "class-11",
      "title": "Class 11 — Part 02",
      "audioUrl": "https://pub-8a0d3971e9fd4d7c991d2300ca9bdca5.r2.dev/lec-033.mp3",
      "durationSeconds": 1368,
      "fileSizeBytes": 5472593,
      "description": null
    },
    {
      "id": "lec-034",
      "number": 34,
      "chapterId": "class-11",
      "title": "Class 11 — Part 03",
      "audioUrl": "https://pub-8a0d3971e9fd4d7c991d2300ca9bdca5.r2.dev/lec-034.mp3",
      "durationSeconds": 1846,
      "fileSizeBytes": 7386637,
      "description": null
    },
    {
      "id": "lec-035",
      "number": 35,
      "chapterId": "class-11",
      "title": "Class 11 — Part 04",
      "audioUrl": "https://pub-8a0d3971e9fd4d7c991d2300ca9bdca5.r2.dev/lec-035.mp3",
      "durationSeconds": 1885,
      "fileSizeBytes": 7542640,
      "description": null
    },
    {
      "id": "lec-036",
      "number": 36,
      "chapterId": "class-12",
      "title": "Class 12 — Part 01",
      "audioUrl": "https://pub-8a0d3971e9fd4d7c991d2300ca9bdca5.r2.dev/lec-036.mp3",
      "durationSeconds": 1948,
      "fileSizeBytes": 7794565,
      "description": null
    },
    {
      "id": "lec-037",
      "number": 37,
      "chapterId": "class-12",
      "title": "Class 12 — Part 02",
      "audioUrl": "https://pub-8a0d3971e9fd4d7c991d2300ca9bdca5.r2.dev/lec-037.mp3",
      "durationSeconds": 1494,
      "fileSizeBytes": 5976547,
      "description": null
    },
    {
      "id": "lec-038",
      "number": 38,
      "chapterId": "class-12",
      "title": "Class 12 — Part 03",
      "audioUrl": "https://pub-8a0d3971e9fd4d7c991d2300ca9bdca5.r2.dev/lec-038.mp3",
      "durationSeconds": 2113,
      "fileSizeBytes": 8454627,
      "description": null
    },
    {
      "id": "lec-039",
      "number": 39,
      "chapterId": "class-12",
      "title": "Class 12 — Part 04",
      "audioUrl": "https://pub-8a0d3971e9fd4d7c991d2300ca9bdca5.r2.dev/lec-039.mp3",
      "durationSeconds": 1773,
      "fileSizeBytes": 7092498,
      "description": null
    },
    {
      "id": "lec-040",
      "number": 40,
      "chapterId": "class-12",
      "title": "Class 12 — Part 05",
      "audioUrl": "https://pub-8a0d3971e9fd4d7c991d2300ca9bdca5.r2.dev/lec-040.mp3",
      "durationSeconds": 1009,
      "fileSizeBytes": 4038679,
      "description": null
    },
    {
      "id": "lec-041",
      "number": 41,
      "chapterId": "class-13",
      "title": "Class 13 — Part 01",
      "audioUrl": "https://pub-8a0d3971e9fd4d7c991d2300ca9bdca5.r2.dev/lec-041.mp3",
      "durationSeconds": 1944,
      "fileSizeBytes": 7776593,
      "description": null
    },
    {
      "id": "lec-042",
      "number": 42,
      "chapterId": "class-13",
      "title": "Class 13 — Part 02",
      "audioUrl": "https://pub-8a0d3971e9fd4d7c991d2300ca9bdca5.r2.dev/lec-042.mp3",
      "durationSeconds": 2043,
      "fileSizeBytes": 8172609,
      "description": null
    },
    {
      "id": "lec-043",
      "number": 43,
      "chapterId": "class-13",
      "title": "Class 13 — Part 03",
      "audioUrl": "https://pub-8a0d3971e9fd4d7c991d2300ca9bdca5.r2.dev/lec-043.mp3",
      "durationSeconds": 2212,
      "fileSizeBytes": 8850643,
      "description": null
    },
    {
      "id": "lec-044",
      "number": 44,
      "chapterId": "class-14",
      "title": "Class 14 — Part 01",
      "audioUrl": "https://pub-8a0d3971e9fd4d7c991d2300ca9bdca5.r2.dev/lec-044.mp3",
      "durationSeconds": 1938,
      "fileSizeBytes": 7752664,
      "description": null
    },
    {
      "id": "lec-045",
      "number": 45,
      "chapterId": "class-14",
      "title": "Class 14 — Part 02",
      "audioUrl": "https://pub-8a0d3971e9fd4d7c991d2300ca9bdca5.r2.dev/lec-045.mp3",
      "durationSeconds": 1933,
      "fileSizeBytes": 7734692,
      "description": null
    },
    {
      "id": "lec-046",
      "number": 46,
      "chapterId": "class-14",
      "title": "Class 14 — Part 03",
      "audioUrl": "https://pub-8a0d3971e9fd4d7c991d2300ca9bdca5.r2.dev/lec-046.mp3",
      "durationSeconds": 1723,
      "fileSizeBytes": 6894699,
      "description": null
    },
    {
      "id": "lec-047",
      "number": 47,
      "chapterId": "class-14",
      "title": "Class 14 — Part 04",
      "audioUrl": "https://pub-8a0d3971e9fd4d7c991d2300ca9bdca5.r2.dev/lec-047.mp3",
      "durationSeconds": 1551,
      "fileSizeBytes": 6204648,
      "description": null
    },
    {
      "id": "lec-048",
      "number": 48,
      "chapterId": "class-14",
      "title": "Class 14 — Part 05",
      "audioUrl": "https://pub-8a0d3971e9fd4d7c991d2300ca9bdca5.r2.dev/lec-048.mp3",
      "durationSeconds": 1360,
      "fileSizeBytes": 5442500,
      "description": null
    },
    {
      "id": "lec-049",
      "number": 49,
      "chapterId": "class-15",
      "title": "Class 15 — Part 01",
      "audioUrl": "https://pub-8a0d3971e9fd4d7c991d2300ca9bdca5.r2.dev/lec-049.mp3",
      "durationSeconds": 2346,
      "fileSizeBytes": 9384586,
      "description": null
    },
    {
      "id": "lec-050",
      "number": 50,
      "chapterId": "class-15",
      "title": "Class 15 — Part 02",
      "audioUrl": "https://pub-8a0d3971e9fd4d7c991d2300ca9bdca5.r2.dev/lec-050.mp3",
      "durationSeconds": 2095,
      "fileSizeBytes": 8382633,
      "description": null
    }
  ],
  "dailyBenefits": [
    {
      "id": "benefit-001",
      "text": "Whoever dies knowing that there is no god but Allah enters Paradise.",
      "textArabic": "من مات وهو يعلم أنه لا إله إلا الله دخل الجنة",
      "source": "Sahih Muslim"
    }
  ]
}